odoo/addons/hr_utilization_analysis/README.rst
odoo/addons/hr_utilization_analysis/__init__.py
odoo/addons/hr_utilization_analysis/__manifest__.py
odoo/addons/hr_utilization_analysis/i18n/de.po
odoo/addons/hr_utilization_analysis/i18n/es.po
odoo/addons/hr_utilization_analysis/i18n/fr.po
odoo/addons/hr_utilization_analysis/i18n/hr_utilization_analysis.pot
odoo/addons/hr_utilization_analysis/i18n/pt.po
odoo/addons/hr_utilization_analysis/readme/CONTRIBUTORS.rst
odoo/addons/hr_utilization_analysis/readme/DESCRIPTION.rst
odoo/addons/hr_utilization_analysis/readme/USAGE.rst
odoo/addons/hr_utilization_analysis/report/__init__.py
odoo/addons/hr_utilization_analysis/report/hr_utilization_analysis.py
odoo/addons/hr_utilization_analysis/report/hr_utilization_analysis.xml
odoo/addons/hr_utilization_analysis/security/ir.model.access.csv
odoo/addons/hr_utilization_analysis/static/description/icon.png
odoo/addons/hr_utilization_analysis/static/description/index.html
odoo/addons/hr_utilization_analysis/tests/__init__.py
odoo/addons/hr_utilization_analysis/tests/test_hr_utilization_analysis.py
odoo/addons/hr_utilization_analysis/views/hr_department.xml
odoo/addons/hr_utilization_analysis/views/hr_employee.xml
odoo/addons/hr_utilization_analysis/wizards/__init__.py
odoo/addons/hr_utilization_analysis/wizards/hr_utilization_analysis_wizard.py
odoo/addons/hr_utilization_analysis/wizards/hr_utilization_analysis_wizard.xml
odoo14_addon_hr_utilization_analysis-14.0.2.0.1.dist-info/METADATA
odoo14_addon_hr_utilization_analysis-14.0.2.0.1.dist-info/WHEEL
odoo14_addon_hr_utilization_analysis-14.0.2.0.1.dist-info/top_level.txt
odoo14_addon_hr_utilization_analysis-14.0.2.0.1.dist-info/RECORD
